README.rst
setup.cfg
setup.py
encviewfuse/__init__.py
encviewfuse.egg-info/PKG-INFO
encviewfuse.egg-info/SOURCES.txt
encviewfuse.egg-info/dependency_links.txt
encviewfuse.egg-info/entry_points.txt
encviewfuse.egg-info/requires.txt
encviewfuse.egg-info/top_level.txt
encviewfuse/fuse/EncryptedFuseFs.py
encviewfuse/fuse/_ArgumentParser.py
encviewfuse/fuse/_FileHandleContainer.py
encviewfuse/fuse/_FuseFsBase.py
encviewfuse/fuse/__init__.py