Metadata-Version: 1.1
Name: encviewfuse
Version: 0.3.0
Summary: A fuse implementation of an encrypted view on a given directory.
Home-page: https://github.com/seiferma/encviewfuse
Author: Stephan Seifermann
Author-email: seiferma@t-online.de
License: MIT
Keywords: encryption fuse view
Platform: UNKNOWN
Classifier: Development Status :: 5 - Production/Stable
Classifier: Environment :: No Input/Output (Daemon)
Classifier: Intended Audience :: System Administrators
Classifier: Topic :: System :: Filesystems
Classifier: License :: OSI Approved :: MIT License
Classifier: Operating System :: MacOS :: MacOS X
Classifier: Operating System :: POSIX :: BSD :: FreeBSD
Classifier: Operating System :: POSIX :: Linux
Classifier: Programming Language :: Python :: 3 :: Only
